myprosody/__init__.py
myprosody-20.dist-info/LICENSE.txt
myprosody-20.dist-info/METADATA
myprosody-20.dist-info/WHEEL
myprosody-20.dist-info/top_level.txt
myprosody-20.dist-info/RECORD
