Metadata-Version: 1.1
Name: myprosody
Version: 20
Summary: NEW VERSION: the prosodic features of speech (simultaneous speech) compared to the features of native speech +++ spoken language proficiency level estimator
Home-page: https://github.com/Shahabks/myprosody
Author: Shahab Sabahi
Author-email: sabahi.s@mysol-gc.jp
License: MIT
Keywords: praat speech signal processing phonetics
Platform: UNKNOWN
Classifier: Intended Audience :: Developers
Classifier: Intended Audience :: Science/Research
Classifier: Programming Language :: Python
Classifier: Programming Language :: Python :: 3.7
